kdp/__init__.py
kdp/auto_config.py
kdp/dynamic_pipeline.py
kdp/features.py
kdp/inference/README.md
kdp/inference/__init__.py
kdp/inference/base.py
kdp/layers/cast_to_float.py
kdp/layers/date_encoding_layer.py
kdp/layers/date_parsing_layer.py
kdp/layers/distribution_aware_encoder_layer.py
kdp/layers/distribution_transform_layer.py
kdp/layers/gated_linear_unit_layer.py
kdp/layers/gated_residual_network_layer.py
kdp/layers/global_numerical_embedding_layer.py
kdp/layers/multi_resolution_tabular_attention_layer.py
kdp/layers/numerical_embedding_layer.py
kdp/layers/preserve_dtype.py
kdp/layers/season_layer.py
kdp/layers/tabular_attention_layer.py
kdp/layers/text_preprocessing_layer.py
kdp/layers/time_series/__init__.py
kdp/layers/time_series/auto_lag_selection_layer.py
kdp/layers/time_series/calendar_feature_layer.py
kdp/layers/time_series/differencing_layer.py
kdp/layers/time_series/fft_feature_layer.py
kdp/layers/time_series/lag_feature_layer.py
kdp/layers/time_series/missing_value_handler_layer.py
kdp/layers/time_series/moving_average_layer.py
kdp/layers/time_series/rolling_stats_layer.py
kdp/layers/time_series/seasonal_decomposition_layer.py
kdp/layers/time_series/tsfresh_feature_layer.py
kdp/layers/time_series/wavelet_transform_layer.py
kdp/layers/transformer_block_layer.py
kdp/layers/variable_selection_layer.py
kdp/layers_factory.py
kdp/model_advisor.py
kdp/moe.py
kdp/pipeline.py
kdp/processor.py
kdp/stats.py
kdp/time_series/README.md
kdp/time_series/__init__.py
kdp/time_series/inference.py
kdp-1.11.2.dist-info/LICENSE
kdp-1.11.2.dist-info/METADATA
kdp-1.11.2.dist-info/WHEEL
kdp-1.11.2.dist-info/RECORD
