Metadata-Version: 2.3
Name: kdp
Version: 1.11.2
Summary: Data Preprocessing model based on Keras preprocessing layers
License: MIT
Author: Piotr Laczkowski
Author-email: piotr.laczkowski@gmail.com
Requires-Python: >=3.9,<4.0
Classifier: License :: OSI Approved :: MIT License
Classifier: Programming Language :: Python :: 3
Classifier: Programming Language :: Python :: 3.9
Classifier: Programming Language :: Python :: 3.10
Classifier: Programming Language :: Python :: 3.11
Classifier: Programming Language :: Python :: 3.12
Classifier: Programming Language :: Python :: 3.13
Requires-Dist: loguru (>=0.7.2,<0.8.0)
Requires-Dist: numpy (>=1.22.0)
Requires-Dist: pandas (>=2.2.0,<3.0.0)
Requires-Dist: parameterized (>=0.9.0,<0.10.0)
Requires-Dist: tensorflow (>=2.18.0,<3.0.0)
Requires-Dist: tf-keras (>=2.18.0,<3.0.0)
Project-URL: Documentation, http://piotrlaczkowski.github.io/keras-data-processor/
Project-URL: Repository, https://github.com/piotrlaczkowski/keras-data-processor
